{"cameraMode":{"drawMode":0,"name":"Shaded","section":"Shading Mode"},"sceneLighting":true,"audioPlay":false,"sceneViewState":{"m_AlwaysRefresh":false,"showFog":true,"showSkybox":true,"showFlares":true,"showImageEffects":true,"showParticleSystems":true,"showVisualEffectGraphs":true,"m_FxEnabled":true},"in2DMode":false,"pivot":{"x":40.29520797729492,"y":12.051036834716797,"z":-6.41913366317749},"rotation":{"x":0.0409066304564476,"y":0.8050879240036011,"z":0.06072022765874863,"w":-0.5895748138427734},"size":0.2018260955810547,"orthographic":false}